apt_history
