Metadata-Version: 1.1
Name: apt-history
Version: 0.2.19
Summary: apt history script
Home-page: https://github.com/Metatavu/apt-history
Author: Antti Leppa
Author-email: antti.leppa@metatavu.fi
License: UNKNOWN
Download-URL: https://github.com/Metatavu/apt-history/tarball/0.2.19
Keywords: apt
Platform: UNKNOWN
